autopackage/__init__.py
autopackage/__main__.py
autopackage/parsers/__init__.py
autopackage/parsers/autoparser.py
autopackage/parsers/setup_parser.py
autopackage/program/__init__.py
autopackage/program/fake_portable.py
autopackage/program/statics.py
autopackage/utils/__init__.py
autopackage/utils/utils.py
autopackage-1.2.dist-info/METADATA
autopackage-1.2.dist-info/WHEEL
autopackage-1.2.dist-info/entry_points.txt
autopackage-1.2.dist-info/top_level.txt
autopackage-1.2.dist-info/zip-safe
autopackage-1.2.dist-info/RECORD
